girs/__init__.py
girs/srs.py
girs/feat/__init__.py
girs/feat/geom.py
girs/feat/layers.py
girs/feat/proc.py
girs/geom/__init__.py
girs/geom/envelope.py
girs/rast/__init__.py
girs/rast/parameter.py
girs/rast/proc.py
girs/rast/raster.py
girs/rastfeat/__init__.py
girs/rastfeat/clip.py
girs/rastfeat/rasterize.py
girs/rastfeat/zonal.py
girs/util/__init__.py
girs/util/osu.py
girs/util/stru.py
girs-0.1.2.dist-info/LICENSE.txt
girs-0.1.2.dist-info/METADATA
girs-0.1.2.dist-info/WHEEL
girs-0.1.2.dist-info/top_level.txt
girs-0.1.2.dist-info/RECORD
