Metadata-Version: 2.1
Name: girs
Version: 0.1.2
Summary: gdal/ogr wrapper
Home-page: http://warsa.de/girs/
Author: Jackson Roehrig
Author-email: Jackson.Roehrig@th-koeln.de
License: MIT
Download-URL: https://github.com/JRoehrig/girs
Platform: UNKNOWN
Classifier: Development Status :: 4 - Beta
Classifier: Environment :: Console
Classifier: Intended Audience :: Science/Research
Classifier: License :: OSI Approved :: MIT License
Classifier: Natural Language :: English
Classifier: Operating System :: OS Independent
Classifier: Programming Language :: Python :: 2.7
Classifier: Programming Language :: Python :: 3
Classifier: Topic :: Scientific/Engineering :: GIS
Requires-Dist: numpy
Requires-Dist: scipy
Requires-Dist: pandas
Requires-Dist: gdal
Requires-Dist: matplotlib
